{"v":"5.5.7","meta":{"g":"LottieFiles AE 0.1.20","a":"","k":"","d":"","tc":""},"fr":29.9700012207031,"ip":0,"op":50.0000020365418,"w":4096,"h":4096,"nm":"03_no","ddd":0,"assets":[],"layers":[{"ddd":0,"ind":1,"ty":4,"nm":"sad_mouth","sr":1,"ks":{"o":{"a":0,"k":100,"ix":11},"r":{"a":0,"k":0,"ix":10},"p":{"a":1,"k":[{"i":{"x":0.833,"y":0.833},"o":{"x":0.333,"y":0},"t":0,"s":[2048,2048,0],"to":null,"ti":null},{"i":{"x":0.833,"y":0.833},"o":{"x":0.333,"y":0},"t":5,"s":[1837,2048,0],"to":null,"ti":null},{"i":{"x":0.833,"y":0.833},"o":{"x":0.333,"y":0},"t":13,"s":[2220,2048,0],"to":null,"ti":null},{"i":{"x":0.833,"y":0.833},"o":{"x":0.333,"y":0},"t":22,"s":[1837,2048,0],"to":null,"ti":null},{"i":{"x":0.833,"y":0.833},"o":{"x":0.333,"y":0},"t":31,"s":[2220,2048,0],"to":null,"ti":null},{"t":37.0000015070409,"s":[2048,2048,0]}],"ix":2},"a":{"a":0,"k":[2048,2048,0],"ix":1},"s":{"a":0,"k":[100,100,100],"ix":6}},"ao":0,"shapes":[{"ty":"gr","it":[{"ind":0,"ty":"sh","ix":1,"ks":{"a":0,"k":{"i":[[487.264,21.742],[231.53699999999998,-113.775],[37.958,-136.986],[-75.693,-134.702],[-345.76599999999996,-70.43299999999999],[-497.07,68.20599999999999],[-436.059,136.984],[-383.31899999999996,133.051],[-368.64,123.506],[-367.296,123.308],[-367.492,123.446],[-274.822,59.867999999999995],[-45.173,13.931],[90.99499999999998,19.355999999999998],[366.581,122.813],[367.297,123.308],[367.621,122.847],[369.663,124.154],[397.513,136.98600000000002],[460.084,124.982]],"o":[[345.767,-70.43299999999999],[75.69399999999999,-134.702],[-37.958,-136.986],[-231.53699999999998,-113.775],[-487.263,21.742],[-460.084,124.982],[-397.512,136.98600000000002],[-369.662,124.154],[-367.62,122.847],[-367.296,123.308],[-366.581,122.813],[-90.994,19.355999999999998],[45.174,13.931],[274.823,59.867999999999995],[367.492,123.446],[367.297,123.308],[368.64099999999996,123.506],[383.32,133.051],[436.06,136.984],[497.07,68.20599999999999]],"v":[[452.557,-0.866],[113.041,-129.686],[0,-136.57],[-113.041,-129.686],[-452.556,-0.866],[-474.46,102.913],[-411.548,136.985],[-370.681,124.818],[-367.62,122.847],[-367.296,123.308],[-367.492,123.446],[-137.383,29.58],[0,13.263],[137.384,29.58],[367.492,123.446],[367.297,123.308],[367.621,122.847],[370.682,124.818],[411.549,136.985],[474.46,102.913]],"c":true},"ix":2},"nm":"Path 1","mn":"ADBE Vector Shape - Group","hd":false,"_render":true},{"ty":"fl","c":{"a":0,"k":[0,0.16,0.1467,1],"ix":4},"o":{"a":0,"k":100,"ix":5},"r":1,"bm":0,"nm":"Fill 1","mn":"ADBE Vector Graphic - Fill","hd":false,"_render":true},{"ty":"tr","p":{"a":0,"k":[2068.243,2104.652],"ix":2},"a":{"a":0,"k":[0,0],"ix":1},"s":{"a":0,"k":[100,100],"ix":3},"r":{"a":0,"k":0,"ix":6},"o":{"a":0,"k":100,"ix":7},"sk":{"a":0,"k":0,"ix":4},"sa":{"a":0,"k":0,"ix":5},"nm":"Transform","_render":true}],"nm":"Group 1","np":2,"cix":2,"bm":0,"ix":1,"mn":"ADBE Vector Group","hd":false,"_render":true}],"ip":0,"op":50.0000020365418,"st":0,"bm":0,"completed":true},{"ddd":0,"ind":2,"ty":4,"nm":"eyes","sr":1,"ks":{"o":{"a":0,"k":100,"ix":11},"r":{"a":0,"k":0,"ix":10},"p":{"a":1,"k":[{"i":{"x":0.833,"y":0.833},"o":{"x":0.333,"y":0},"t":0,"s":[2048,2048,0],"to":null,"ti":null},{"i":{"x":0.833,"y":0.833},"o":{"x":0.333,"y":0},"t":5,"s":[1837,2048,0],"to":null,"ti":null},{"i":{"x":0.833,"y":0.833},"o":{"x":0.333,"y":0},"t":13,"s":[2220,2048,0],"to":null,"ti":null},{"i":{"x":0.833,"y":0.833},"o":{"x":0.333,"y":0},"t":22,"s":[1837,2048,0],"to":null,"ti":null},{"i":{"x":0.833,"y":0.833},"o":{"x":0.333,"y":0},"t":31,"s":[2220,2048,0],"to":null,"ti":null},{"t":37.0000015070409,"s":[2048,2048,0]}],"ix":2},"a":{"a":0,"k":[2048,2048,0],"ix":1},"s":{"a":0,"k":[100,100,100],"ix":6}},"ao":0,"shapes":[{"ty":"gr","it":[{"ind":0,"ty":"sh","ix":1,"ks":{"a":0,"k":{"i":[[214.777,-118.618],[118.618,214.777],[-214.777,118.618],[-118.618,-214.777]],"o":[[214.777,118.618],[-118.618,214.777],[-214.777,-118.618],[118.618,-214.777]],"v":[[214.777,0],[0,214.777],[-214.777,0],[0,-214.777]],"c":true},"ix":2},"nm":"Path 1","mn":"ADBE Vector Shape - Group","hd":false,"_render":true},{"ty":"fl","c":{"a":0,"k":[0,0.16,0.1467,1],"ix":4},"o":{"a":0,"k":100,"ix":5},"r":1,"bm":0,"nm":"Fill 1","mn":"ADBE Vector Graphic - Fill","hd":false,"_render":true},{"ty":"tr","p":{"a":0,"k":[2806.446,1521.037],"ix":2},"a":{"a":0,"k":[0,0],"ix":1},"s":{"a":0,"k":[100,100],"ix":3},"r":{"a":0,"k":0,"ix":6},"o":{"a":0,"k":100,"ix":7},"sk":{"a":0,"k":0,"ix":4},"sa":{"a":0,"k":0,"ix":5},"nm":"Transform","_render":true}],"nm":"Group 1","np":2,"cix":2,"bm":0,"ix":1,"mn":"ADBE Vector Group","hd":false,"_render":true},{"ty":"gr","it":[{"ind":0,"ty":"sh","ix":1,"ks":{"a":0,"k":{"i":[[214.777,-118.618],[118.618,214.777],[-214.777,118.618],[-118.618,-214.777]],"o":[[214.777,118.618],[-118.618,214.777],[-214.777,-118.618],[118.618,-214.777]],"v":[[214.777,0],[0,214.777],[-214.777,0],[0,-214.777]],"c":true},"ix":2},"nm":"Path 1","mn":"ADBE Vector Shape - Group","hd":false,"_render":true},{"ty":"fl","c":{"a":0,"k":[0,0.16,0.1467,1],"ix":4},"o":{"a":0,"k":100,"ix":5},"r":1,"bm":0,"nm":"Fill 1","mn":"ADBE Vector Graphic - Fill","hd":false,"_render":true},{"ty":"tr","p":{"a":0,"k":[1342.782,1521.037],"ix":2},"a":{"a":0,"k":[0,0],"ix":1},"s":{"a":0,"k":[100,100],"ix":3},"r":{"a":0,"k":0,"ix":6},"o":{"a":0,"k":100,"ix":7},"sk":{"a":0,"k":0,"ix":4},"sa":{"a":0,"k":0,"ix":5},"nm":"Transform","_render":true}],"nm":"Group 2","np":2,"cix":2,"bm":0,"ix":2,"mn":"ADBE Vector Group","hd":false,"_render":true}],"ip":0,"op":50.0000020365418,"st":0,"bm":0,"completed":true},{"ddd":0,"ind":3,"ty":4,"nm":"head_fushing","sr":1,"ks":{"o":{"a":0,"k":100,"ix":11},"r":{"a":0,"k":0,"ix":10},"p":{"a":1,"k":[{"i":{"x":0.833,"y":0.833},"o":{"x":0.333,"y":0},"t":0,"s":[2048,2196,0],"to":null,"ti":null},{"i":{"x":0.833,"y":0.833},"o":{"x":0.333,"y":0},"t":5,"s":[1837,2196,0],"to":null,"ti":null},{"i":{"x":0.833,"y":0.833},"o":{"x":0.333,"y":0},"t":13,"s":[2220,2196,0],"to":null,"ti":null},{"i":{"x":0.833,"y":0.833},"o":{"x":0.333,"y":0},"t":22,"s":[1837,2196,0],"to":null,"ti":null},{"i":{"x":0.833,"y":0.833},"o":{"x":0.333,"y":0},"t":31,"s":[2220,2196,0],"to":null,"ti":null},{"t":37.0000015070409,"s":[2048,2196,0]}],"ix":2},"a":{"a":0,"k":[2048,2048,0],"ix":1},"s":{"a":0,"k":[100,100,100],"ix":6}},"ao":0,"shapes":[{"ty":"gr","it":[{"ind":0,"ty":"sh","ix":1,"ks":{"a":0,"k":{"i":[[214.777,-118.618],[118.618,214.777],[-214.777,118.618],[-118.618,-214.777]],"o":[[214.777,118.618],[-118.618,214.777],[-214.777,-118.618],[118.618,-214.777]],"v":[[214.777,0],[0,214.777],[-214.777,0],[0,-214.777]],"c":true},"ix":2},"nm":"Path 1","mn":"ADBE Vector Shape - Group","hd":false,"_render":true},{"ty":"fl","c":{"a":0,"k":[0.0039,0.6157,0.5686,1],"ix":4},"o":{"a":0,"k":100,"ix":5},"r":1,"bm":0,"nm":"Fill 1","mn":"ADBE Vector Graphic - Fill","hd":false,"_render":true},{"ty":"tr","p":{"a":0,"k":[3405.037,2095.727],"ix":2},"a":{"a":0,"k":[0,0],"ix":1},"s":{"a":0,"k":[100,100],"ix":3},"r":{"a":0,"k":0,"ix":6},"o":{"a":0,"k":100,"ix":7},"sk":{"a":0,"k":0,"ix":4},"sa":{"a":0,"k":0,"ix":5},"nm":"Transform","_render":true}],"nm":"Group 1","np":2,"cix":2,"bm":0,"ix":1,"mn":"ADBE Vector Group","hd":false,"_render":true},{"ty":"gr","it":[{"ind":0,"ty":"sh","ix":1,"ks":{"a":0,"k":{"i":[[214.777,-118.618],[118.618,214.777],[-214.777,118.618],[-118.618,-214.777]],"o":[[214.777,118.618],[-118.618,214.777],[-214.777,-118.618],[118.618,-214.777]],"v":[[214.777,0],[0,214.777],[-214.777,0],[0,-214.777]],"c":true},"ix":2},"nm":"Path 1","mn":"ADBE Vector Shape - Group","hd":false,"_render":true},{"ty":"fl","c":{"a":0,"k":[0.0039,0.6157,0.5686,1],"ix":4},"o":{"a":0,"k":100,"ix":5},"r":1,"bm":0,"nm":"Fill 1","mn":"ADBE Vector Graphic - Fill","hd":false,"_render":true},{"ty":"tr","p":{"a":0,"k":[744.191,2095.727],"ix":2},"a":{"a":0,"k":[0,0],"ix":1},"s":{"a":0,"k":[100,100],"ix":3},"r":{"a":0,"k":0,"ix":6},"o":{"a":0,"k":100,"ix":7},"sk":{"a":0,"k":0,"ix":4},"sa":{"a":0,"k":0,"ix":5},"nm":"Transform","_render":true}],"nm":"Group 2","np":2,"cix":2,"bm":0,"ix":2,"mn":"ADBE Vector Group","hd":false,"_render":true}],"ip":0,"op":50.0000020365418,"st":0,"bm":0,"completed":true},{"ddd":0,"ind":4,"ty":4,"nm":"head_highlight","sr":1,"ks":{"o":{"a":0,"k":100,"ix":11},"r":{"a":1,"k":[{"i":{"x":[0.833],"y":[0.833]},"o":{"x":[0.333],"y":[0]},"t":0,"s":[0]},{"i":{"x":[0.833],"y":[0.833]},"o":{"x":[0.333],"y":[0]},"t":5,"s":[-13]},{"i":{"x":[0.833],"y":[0.833]},"o":{"x":[0.333],"y":[0]},"t":13,"s":[13]},{"i":{"x":[0.833],"y":[0.833]},"o":{"x":[0.333],"y":[0]},"t":22,"s":[-13]},{"i":{"x":[0.833],"y":[0.833]},"o":{"x":[0.333],"y":[0]},"t":31,"s":[13]},{"t":37.0000015070409,"s":[0]}],"ix":10},"p":{"a":0,"k":[2048,2048,0],"ix":2},"a":{"a":0,"k":[2048,2048,0],"ix":1},"s":{"a":0,"k":[100,100,100],"ix":6}},"ao":0,"shapes":[{"ty":"gr","it":[{"ind":0,"ty":"sh","ix":1,"ks":{"a":0,"k":{"i":[[430.615,-329.868],[363.706,-351.4],[368.809,-461.074],[544.901,-501.367],[689.553,-486.964],[671.399,-372.748],[504.654,-347.95099999999996]],"o":[[392.81399999999996,-329.868],[345.668,-422.10699999999997],[475.10200000000003,-488.201],[653.7579999999999,-514.884],[699.271,-408.497],[568.461,-360],[436.581,-330.589]],"v":[[424.765,-329.868],[355.432,-383.794],[407.122,-470.862],[614.583,-509.99],[694.424,-447.719],[632.153,-367.877],[442.5,-332.104]],"c":true},"ix":2},"nm":"Path 1","mn":"ADBE Vector Shape - Group","hd":false,"_render":true},{"ind":1,"ty":"sh","ix":2,"ks":{"a":0,"k":{"i":[[-591.253,514.885],[-639.121,512.484],[-699.2719999999999,446.927],[-272.024,-163.332],[114.32100000000001,-332.501],[138.209,-219.35600000000002],[-411.78299999999996,189.15299999999996]],"o":[[-628.285,514.885],[-684.775,489.879],[-526.933,99.00999999999999],[71.068,-345.78499999999997],[151.44600000000003,-262.703],[-178.57299999999998,-50.86200000000002],[-565.8979999999999,500.27099999999996]],"v":[[-617.611,514.885],[-649.352,507.427],[-681.723,411.48],[36.041,-327.188],[132.872,-297.614],[103.298,-200.782],[-553.406,475.056]],"c":true},"ix":2},"nm":"Path 2","mn":"ADBE Vector Shape - Group","hd":false,"_render":true},{"ty":"mm","mm":1,"nm":"Merge Paths 1","mn":"ADBE Vector Filter - Merge","hd":false,"_render":true},{"ty":"fl","c":{"a":0,"k":[0.9647,0.9569,0.9804,1],"ix":4},"o":{"a":0,"k":100,"ix":5},"r":1,"bm":0,"nm":"Fill 1","mn":"ADBE Vector Graphic - Fill","hd":false,"_render":true},{"ty":"tr","p":{"a":0,"k":[1125.365,870.057],"ix":2},"a":{"a":0,"k":[0,0],"ix":1},"s":{"a":0,"k":[100,100],"ix":3},"r":{"a":0,"k":0,"ix":6},"o":{"a":0,"k":100,"ix":7},"sk":{"a":0,"k":0,"ix":4},"sa":{"a":0,"k":0,"ix":5},"nm":"Transform","_render":true}],"nm":"Group 1","np":4,"cix":2,"bm":0,"ix":1,"mn":"ADBE Vector Group","hd":false,"_render":true}],"ip":0,"op":50.0000020365418,"st":0,"bm":0,"completed":true},{"ddd":0,"ind":5,"ty":4,"nm":"head_stroke","sr":1,"ks":{"o":{"a":0,"k":100,"ix":11},"r":{"a":0,"k":0,"ix":10},"p":{"a":0,"k":[2048,2048,0],"ix":2},"a":{"a":0,"k":[2048,2048,0],"ix":1},"s":{"a":0,"k":[100,100,100],"ix":6}},"ao":0,"shapes":[{"ty":"gr","it":[{"ind":0,"ty":"sh","ix":1,"ks":{"a":0,"k":{"i":[[1122.879,-2036.403],[-2036.403,-1122.879],[-1122.873,2036.404],[2036.403,1122.874]],"o":[[-1122.873,-2036.403],[-2036.403,1122.874],[1122.879,2036.404],[2036.403,-1122.879]],"v":[[0.003,-2036.403],[-2036.403,-0.003],[0.003,2036.404],[2036.403,-0.003]],"c":true},"ix":2},"nm":"Path 1","mn":"ADBE Vector Shape - Group","hd":false,"_render":true},{"ind":1,"ty":"sh","ix":2,"ks":{"a":0,"k":{"i":[[-1019.237,-1845.49],[1845.491,-1019.2370000000001],[1019.2370000000001,1845.491],[-1845.491,1019.2379999999999]],"o":[[1019.2370000000001,-1845.49],[1845.491,1019.2379999999999],[-1019.237,1845.491],[-1845.491,-1019.2370000000001]],"v":[[0.003,-1845.49],[1845.491,-0.003],[0.003,1845.491],[-1845.491,-0.003]],"c":true},"ix":2},"nm":"Path 2","mn":"ADBE Vector Shape - Group","hd":false,"_render":true},{"ty":"mm","mm":1,"nm":"Merge Paths 1","mn":"ADBE Vector Filter - Merge","hd":false,"_render":true},{"ty":"fl","c":{"a":0,"k":[0,0.16,0.1467,1],"ix":4},"o":{"a":0,"k":100,"ix":5},"r":1,"bm":0,"nm":"Fill 1","mn":"ADBE Vector Graphic - Fill","hd":false,"_render":true},{"ty":"tr","p":{"a":0,"k":[2058.597,2055.597],"ix":2},"a":{"a":0,"k":[0,0],"ix":1},"s":{"a":0,"k":[100,100],"ix":3},"r":{"a":0,"k":0,"ix":6},"o":{"a":0,"k":100,"ix":7},"sk":{"a":0,"k":0,"ix":4},"sa":{"a":0,"k":0,"ix":5},"nm":"Transform","_render":true}],"nm":"Group 1","np":4,"cix":2,"bm":0,"ix":1,"mn":"ADBE Vector Group","hd":false,"_render":true}],"ip":0,"op":50.0000020365418,"st":0,"bm":0,"completed":true},{"ddd":0,"ind":6,"ty":4,"nm":"head_shadow","sr":1,"ks":{"o":{"a":0,"k":100,"ix":11},"r":{"a":1,"k":[{"i":{"x":[0.833],"y":[0.833]},"o":{"x":[0.333],"y":[0]},"t":0,"s":[0]},{"i":{"x":[0.833],"y":[0.833]},"o":{"x":[0.333],"y":[0]},"t":5,"s":[-13]},{"i":{"x":[0.833],"y":[0.833]},"o":{"x":[0.333],"y":[0]},"t":13,"s":[13]},{"i":{"x":[0.833],"y":[0.833]},"o":{"x":[0.333],"y":[0]},"t":22,"s":[-13]},{"i":{"x":[0.833],"y":[0.833]},"o":{"x":[0.333],"y":[0]},"t":31,"s":[13]},{"t":37.0000015070409,"s":[0]}],"ix":10},"p":{"a":0,"k":[2048,2048,0],"ix":2},"a":{"a":0,"k":[2048,2048,0],"ix":1},"s":{"a":1,"k":[{"i":{"x":[0.833,0.833,0.833],"y":[0.833,0.833,0.833]},"o":{"x":[0.167,0.167,0.167],"y":[0.167,0.167,0.167]},"t":0,"s":[106.504,100,100]},{"i":{"x":[0.833,0.833,0.833],"y":[0.833,0.833,0.833]},"o":{"x":[0.167,0.167,0.167],"y":[0.167,0.167,0.167]},"t":5,"s":[99.301,100,100]},{"t":13.0000005295009,"s":[104.478,100,100]}],"ix":6}},"ao":0,"shapes":[{"ty":"gr","it":[{"ind":0,"ty":"sh","ix":1,"ks":{"a":1,"k":[{"i":{"x":0.833,"y":0.833},"o":{"x":0.333,"y":0},"t":0,"s":[{"i":[[188.9240000000001,-1874.658],[-968.392,-1871.492],[716.503,-993.816],[-78.2220000000001,1774.273],[-907.782,1874.658],[1028.238,1035.3509999999999]],"o":[[-907.782,-1874.658],[-78.2220000000001,-1774.272],[716.503,954.166],[-968.392,1871.499],[188.9240000000001,1874.658],[1028.238,-1035.345]],"v":[[-846.427,-1874.658],[-1028.238,-1865.733],[716.503,-19.823],[-1028.238,1865.734],[-846.427,1874.658],[1028.238,0.001]],"c":true}]},{"i":{"x":0.833,"y":0.833},"o":{"x":0.333,"y":0},"t":5,"s":[{"i":[[188.9240000000001,-1874.658],[-968.392,-1871.492],[618.681,-999.823],[-78.2220000000001,1774.273],[-907.782,1874.658],[1028.238,1035.3509999999999]],"o":[[-907.782,-1874.658],[-78.2220000000001,-1774.272],[618.681,948.1600000000001],[-968.392,1871.499],[188.9240000000001,1874.658],[1028.238,-1035.345]],"v":[[-846.427,-1874.658],[-1028.238,-1865.733],[618.681,-25.829],[-1028.238,1865.734],[-846.427,1874.658],[1028.238,0.001]],"c":true}]},{"i":{"x":0.833,"y":0.833},"o":{"x":0.333,"y":0},"t":13,"s":[{"i":[[188.9240000000001,-1874.658],[-968.392,-1871.492],[840.786,-1061.605],[-78.2220000000001,1774.273],[-907.782,1874.658],[1028.238,1035.3509999999999]],"o":[[-907.782,-1874.658],[-78.2220000000001,-1774.272],[840.786,886.379],[-968.392,1871.499],[188.9240000000001,1874.658],[1028.238,-1035.345]],"v":[[-846.427,-1874.658],[-1028.238,-1865.733],[840.786,-87.611],[-1028.238,1865.734],[-846.427,1874.658],[1028.238,0.001]],"c":true}]},{"i":{"x":0.833,"y":0.833},"o":{"x":0.333,"y":0},"t":22,"s":[{"i":[[188.9240000000001,-1874.658],[-968.392,-1871.492],[618.681,-999.823],[-78.2220000000001,1774.273],[-907.782,1874.658],[1028.238,1035.3509999999999]],"o":[[-907.782,-1874.658],[-78.2220000000001,-1774.272],[618.681,948.1600000000001],[-968.392,1871.499],[188.9240000000001,1874.658],[1028.238,-1035.345]],"v":[[-846.427,-1874.658],[-1028.238,-1865.733],[618.681,-25.829],[-1028.238,1865.734],[-846.427,1874.658],[1028.238,0.001]],"c":true}]},{"i":{"x":0.833,"y":0.833},"o":{"x":0.333,"y":0},"t":31,"s":[{"i":[[188.9240000000001,-1874.658],[-968.392,-1871.492],[840.786,-1061.605],[-78.2220000000001,1774.273],[-907.782,1874.658],[1028.238,1035.3509999999999]],"o":[[-907.782,-1874.658],[-78.2220000000001,-1774.272],[840.786,886.379],[-968.392,1871.499],[188.9240000000001,1874.658],[1028.238,-1035.345]],"v":[[-846.427,-1874.658],[-1028.238,-1865.733],[840.786,-87.611],[-1028.238,1865.734],[-846.427,1874.658],[1028.238,0.001]],"c":true}]},{"t":37.0000015070409,"s":[{"i":[[188.9240000000001,-1874.658],[-968.392,-1871.492],[716.503,-993.816],[-78.2220000000001,1774.273],[-907.782,1874.658],[1028.238,1035.3509999999999]],"o":[[-907.782,-1874.658],[-78.2220000000001,-1774.272],[716.503,954.166],[-968.392,1871.499],[188.9240000000001,1874.658],[1028.238,-1035.345]],"v":[[-846.427,-1874.658],[-1028.238,-1865.733],[716.503,-19.823],[-1028.238,1865.734],[-846.427,1874.658],[1028.238,0.001]],"c":true}]}],"ix":2},"nm":"Path 1","mn":"ADBE Vector Shape - Group","hd":false,"_render":true},{"ty":"fl","c":{"a":0,"k":[0.2748,0.9852,0.926,1],"ix":4},"o":{"a":0,"k":100,"ix":5},"r":1,"bm":0,"nm":"Fill 1","mn":"ADBE Vector Graphic - Fill","hd":false,"_render":true},{"ty":"tr","p":{"a":0,"k":[2907.805,2059.571],"ix":2},"a":{"a":0,"k":[0,0],"ix":1},"s":{"a":0,"k":[100,100],"ix":3},"r":{"a":0,"k":0,"ix":6},"o":{"a":0,"k":100,"ix":7},"sk":{"a":0,"k":0,"ix":4},"sa":{"a":0,"k":0,"ix":5},"nm":"Transform","_render":true}],"nm":"Group 1","np":2,"cix":2,"bm":0,"ix":1,"mn":"ADBE Vector Group","hd":false,"_render":true}],"ip":0,"op":50.0000020365418,"st":0,"bm":0,"completed":true},{"ddd":0,"ind":7,"ty":4,"nm":"head_body","sr":1,"ks":{"o":{"a":0,"k":100,"ix":11},"r":{"a":0,"k":0,"ix":10},"p":{"a":0,"k":[2048,2048,0],"ix":2},"a":{"a":0,"k":[2048,2048,0],"ix":1},"s":{"a":0,"k":[100,100,100],"ix":6}},"ao":0,"shapes":[{"ty":"gr","it":[{"ind":0,"ty":"sh","ix":1,"ks":{"a":0,"k":{"i":[[1034.639,1876.391],[-1876.391,1034.6390000000001],[-1034.6390000000001,-1876.39],[1876.39,-1034.639]],"o":[[-1034.6390000000001,1876.391],[-1876.391,-1034.639],[1034.639,-1876.39],[1876.39,1034.6390000000001]],"v":[[0.011,1876.391],[-1876.391,-0.011],[0.011,-1876.39],[1876.39,-0.011]],"c":true},"ix":2},"nm":"Path 1","mn":"ADBE Vector Shape - Group","hd":false,"_render":true},{"ty":"fl","c":{"a":0,"k":[0.44,1,0.9533,1],"ix":4},"o":{"a":0,"k":100,"ix":5},"r":1,"bm":0,"nm":"Fill 1","mn":"ADBE Vector Graphic - Fill","hd":false,"_render":true},{"ty":"tr","p":{"a":0,"k":[2058.594,2055.6],"ix":2},"a":{"a":0,"k":[0,0],"ix":1},"s":{"a":0,"k":[100,100],"ix":3},"r":{"a":0,"k":0,"ix":6},"o":{"a":0,"k":100,"ix":7},"sk":{"a":0,"k":0,"ix":4},"sa":{"a":0,"k":0,"ix":5},"nm":"Transform","_render":true}],"nm":"Group 1","np":2,"cix":2,"bm":0,"ix":1,"mn":"ADBE Vector Group","hd":false,"_render":true}],"ip":0,"op":50.0000020365418,"st":0,"bm":0,"completed":true}],"markers":[],"__complete":true}